{
"type": "FeatureCollection",
"features": [
{ "type": "Feature", "properties": { "id": 1, "title": "Born Secret (Cash for Kryptonite)", "websiteUrl": "documents/born_secret.html", "caption": "" }, "geometry": { "type": "Point", "coordinates": [ -88.811245, 37.103683 ] } }
]
}
