{
"type": "FeatureCollection",
"name": "born_secret",
"crs": { "type": "name", "properties": { "name": "urn:ogc:def:crs:OGC:1.3:CRS84" } },
"features": [
{ "type": "Feature", "properties": { "title": "Born Secret (Cash for Kryptonite)", "videoSrc": "https:\/\/player.vimeo.com\/video\/374696808", "caption": "by Jeremy Bolen, Brian Holmes, Brian Kirkbride" }, "geometry": { "type": "Point", "coordinates": [ -88.811245, 37.103683 ] } }
]
}
