{
"type": "FeatureCollection",
"name": "confluence_ecologies",
"crs": { "type": "name", "properties": { "name": "urn:ogc:def:crs:OGC:1.3:CRS84" } },
"features": [
{ "type": "Feature", "properties": { "title": "Confluence Ecologies", "videoSrc": "https://player.vimeo.com/video/451562484" }, "geometry": { "type": "Point", "coordinates": [ -89.374, 37.09 ] } }
]
}
